[
  {
    "name": "Sprint 9 Test run for Automated",
    "assignedTo": "Sam",
    "projectId": "id_1776313515484_xl29y9a",
    "planId": "id_1776239106353_57k0zkz",
    "scope": "suite",
    "moduleName": "Module B",
    "suiteName": "Suite B",
    "status": "In Progress",
    "createdAt": "2026-04-16",
    "results": [
      {
        "testCaseId": "id_1776313889020_tjhx9uh",
        "status": "Passed"
      },
      {
        "testCaseId": "id_1776313889035_d98cns1",
        "status": "Passed"
      },
      {
        "testCaseId": "id_1776313889045_up9r2mo",
        "status": "Passed"
      },
      {
        "testCaseId": "id_1776313889057_t7cjn82",
        "status": "Passed"
      },
      {
        "testCaseId": "id_1776313889068_ohzze21",
        "status": "Passed"
      },
      {
        "testCaseId": "id_1776313889080_ot7x0bi",
        "status": "Passed"
      },
      {
        "testCaseId": "id_1776313889092_z1mtjov",
        "status": "Passed"
      },
      {
        "testCaseId": "id_1776313889103_qqsij7t",
        "status": "Passed"
      },
      {
        "testCaseId": "id_1776313889116_k7st03z",
        "status": "Passed"
      },
      {
        "testCaseId": "id_1776313889127_leloxzw",
        "status": "Passed"
      },
      {
        "testCaseId": "id_1776313889144_otgex5e",
        "status": "Passed"
      },
      {
        "testCaseId": "id_1776313889154_aliurew",
        "status": "Passed"
      },
      {
        "testCaseId": "id_1776313889165_em2eotg",
        "status": "Passed"
      },
      {
        "testCaseId": "id_1776313889175_7dko7sw",
        "status": "Passed"
      },
      {
        "testCaseId": "id_1776313889187_ovvyiss",
        "status": "Passed"
      },
      {
        "testCaseId": "id_1776313889197_u7b47pw",
        "status": "Passed"
      },
      {
        "testCaseId": "id_1776313889209_fv1oxly",
        "status": "Passed"
      },
      {
        "testCaseId": "id_1776313889219_o3p5r0r",
        "status": "Passed"
      },
      {
        "testCaseId": "id_1776313889236_iedeh7v",
        "status": "Passed"
      },
      {
        "testCaseId": "id_1776313889286_7nkifl9",
        "status": "Passed"
      },
      {
        "testCaseId": "id_1776313889294_20kufq7",
        "status": "Passed"
      },
      {
        "testCaseId": "id_1776313889300_gdz38qk",
        "status": "Passed"
      },
      {
        "testCaseId": "id_1776313889308_94kapsn",
        "status": "Passed"
      },
      {
        "testCaseId": "id_1776313889315_2h82unk",
        "status": "Passed"
      },
      {
        "testCaseId": "id_1776313889322_ju6wxdf",
        "status": "Passed"
      },
      {
        "testCaseId": "id_1776313889334_by9vp8h",
        "status": "Passed"
      },
      {
        "testCaseId": "id_1776313889341_faew3hm",
        "status": "Passed"
      },
      {
        "testCaseId": "id_1776313889349_w64l1fp",
        "status": "Passed"
      },
      {
        "testCaseId": "id_1776313889357_3408nal",
        "status": "Passed"
      },
      {
        "testCaseId": "id_1776313889364_xnmjowe",
        "status": "Passed"
      },
      {
        "testCaseId": "id_1776313889372_eemgm0s",
        "status": "Passed"
      },
      {
        "testCaseId": "id_1776313889380_p1dumj5",
        "status": "Passed"
      },
      {
        "testCaseId": "id_1776313889388_nxyhnar",
        "status": "Passed"
      },
      {
        "testCaseId": "id_1776313889396_e69ai2o",
        "status": "Passed"
      },
      {
        "testCaseId": "id_1776313889405_3ecwe3f",
        "status": "Passed"
      },
      {
        "testCaseId": "id_1776313889436_7j67u6c",
        "status": "Passed"
      },
      {
        "testCaseId": "id_1776313889443_tzypepi",
        "status": "Passed"
      },
      {
        "testCaseId": "id_1776313889449_4om2m8o",
        "status": "Passed"
      },
      {
        "testCaseId": "id_1776313889455_xu9edc6",
        "status": "Passed"
      },
      {
        "testCaseId": "id_1776313889469_y4x3z2x",
        "status": "Passed"
      },
      {
        "testCaseId": "id_1776313889476_lumy64m",
        "status": "Passed"
      },
      {
        "testCaseId": "id_1776313889483_55k6wek",
        "status": "Passed"
      },
      {
        "testCaseId": "id_1776313889491_m691niu",
        "status": "Passed"
      },
      {
        "testCaseId": "id_1776313889498_u8yc8o3",
        "status": "Passed"
      },
      {
        "testCaseId": "id_1776313889505_yefjssc",
        "status": "Passed"
      },
      {
        "testCaseId": "id_1776313889512_f41pb0x",
        "status": "Passed"
      },
      {
        "testCaseId": "id_1776313889519_el8hy2e",
        "status": "Passed"
      },
      {
        "testCaseId": "id_1776313889524_4ihvcz9",
        "status": "Passed"
      },
      {
        "testCaseId": "id_1776313889532_7ak7309",
        "status": "Passed"
      },
      {
        "testCaseId": "id_1776313889540_61jt8si",
        "status": "Passed"
      },
      {
        "testCaseId": "id_1776313889546_i8sfd7z",
        "status": "Passed"
      },
      {
        "testCaseId": "id_1776313889553_dmonenc",
        "status": "Passed"
      },
      {
        "testCaseId": "id_1776313889558_9mlmrjy",
        "status": "Passed"
      },
      {
        "testCaseId": "id_1776313889564_bxgznq6",
        "status": "Passed"
      },
      {
        "testCaseId": "id_1776313889569_bn4y47l",
        "status": "Passed"
      },
      {
        "testCaseId": "id_1776313889575_p1mav31",
        "status": "Passed"
      },
      {
        "testCaseId": "id_1776313889582_ohvfbj5",
        "status": "Passed"
      },
      {
        "testCaseId": "id_1776313889588_hs1zgor",
        "status": "Passed"
      },
      {
        "testCaseId": "id_1776313889594_1xhkcg6",
        "status": "Passed"
      },
      {
        "testCaseId": "id_1776313889626_31fq8w2",
        "status": "Passed"
      },
      {
        "testCaseId": "id_1776313889632_ir3x5cz",
        "status": "Passed"
      },
      {
        "testCaseId": "id_1776313889638_nmyxqcs",
        "status": "Passed"
      },
      {
        "testCaseId": "id_1776313889647_d6ygjo5",
        "status": "Passed"
      },
      {
        "testCaseId": "id_1776313889655_a2s1tny",
        "status": "Passed"
      },
      {
        "testCaseId": "id_1776313889662_zjyp512",
        "status": "Passed"
      },
      {
        "testCaseId": "id_1776313889669_aqb12ga",
        "status": "Passed"
      },
      {
        "testCaseId": "id_1776313889676_utme90d",
        "status": "Passed"
      },
      {
        "testCaseId": "id_1776313889684_6w1pwql",
        "status": "Passed"
      },
      {
        "testCaseId": "id_1776313889691_wdsrw4r",
        "status": "Passed"
      },
      {
        "testCaseId": "id_1776313889699_nez2341",
        "status": "Passed"
      },
      {
        "testCaseId": "id_1776313889706_0vmvapo",
        "status": "Passed"
      },
      {
        "testCaseId": "id_1776313889713_6lvgtgp",
        "status": "Passed"
      },
      {
        "testCaseId": "id_1776313889721_iai7afl",
        "status": "Passed"
      },
      {
        "testCaseId": "id_1776313889729_cekhyd0",
        "status": "Passed"
      },
      {
        "testCaseId": "id_1776313889738_iip4suv",
        "status": "Passed"
      },
      {
        "testCaseId": "id_1776313889747_mx8r6bi",
        "status": "Passed"
      },
      {
        "testCaseId": "id_1776313889755_zxli28o",
        "status": "Passed"
      },
      {
        "testCaseId": "id_1776313889764_ip287at",
        "status": "Passed"
      },
      {
        "testCaseId": "id_1776313889797_o3fq4b3",
        "status": "Passed"
      },
      {
        "testCaseId": "id_1776313889803_5exnjrf",
        "status": "Passed"
      },
      {
        "testCaseId": "id_1776313889809_0e7evkk",
        "status": "Passed"
      },
      {
        "testCaseId": "id_1776313889817_tclugot",
        "status": "Passed"
      },
      {
        "testCaseId": "id_1776313889825_oer2sot",
        "status": "Passed"
      },
      {
        "testCaseId": "id_1776313889833_n1nep3q",
        "status": "Passed"
      },
      {
        "testCaseId": "id_1776313889841_2eu7yke",
        "status": "Passed"
      },
      {
        "testCaseId": "id_1776313889849_upi40yz",
        "status": "Passed"
      },
      {
        "testCaseId": "id_1776313889859_e451ary",
        "status": "Passed"
      },
      {
        "testCaseId": "id_1776313889867_84u4r5k",
        "status": "Passed"
      },
      {
        "testCaseId": "id_1776313889875_894ge7r",
        "status": "Passed"
      },
      {
        "testCaseId": "id_1776313889883_gghs5oe",
        "status": "Passed"
      },
      {
        "testCaseId": "id_1776313889892_fz1bso1",
        "status": "Passed"
      },
      {
        "testCaseId": "id_1776313889900_1yq16o8",
        "status": "Passed"
      },
      {
        "testCaseId": "id_1776313889908_jjnijj2",
        "status": "Passed"
      },
      {
        "testCaseId": "id_1776313889919_x0km20m",
        "status": "Passed"
      },
      {
        "testCaseId": "id_1776313889929_i21wry3",
        "status": "Passed"
      },
      {
        "testCaseId": "id_1776313889938_1hjsy8c",
        "status": "Passed"
      },
      {
        "testCaseId": "id_1776313889946_6nlby5g",
        "status": "Passed"
      },
      {
        "testCaseId": "id_1776313889954_qmckguk",
        "status": "Passed"
      },
      {
        "testCaseId": "id_1776313889990_y8734ly",
        "status": "Passed"
      },
      {
        "testCaseId": "id_1776313889996_khoyvrj",
        "status": "Passed"
      },
      {
        "testCaseId": "id_1776313890003_djq4bo9",
        "status": "Passed"
      },
      {
        "testCaseId": "id_1776313890011_3qysv9k",
        "status": "Passed"
      },
      {
        "testCaseId": "id_1776313890019_05kamnt",
        "status": "Passed"
      },
      {
        "testCaseId": "id_1776313890028_qm35le9",
        "status": "Passed"
      },
      {
        "testCaseId": "id_1776313890036_3ich7o5",
        "status": "Passed"
      },
      {
        "testCaseId": "id_1776313890044_8i81qhm",
        "status": "Passed"
      },
      {
        "testCaseId": "id_1776313890054_uiu1713",
        "status": "Failed",
        "stepComments": {
          "1": "It didnt work"
        }
      },
      {
        "testCaseId": "id_1776313890062_vg0yymr",
        "status": "Passed"
      },
      {
        "testCaseId": "id_1776313890071_3t4q2kw",
        "status": "Passed"
      },
      {
        "testCaseId": "id_1776313890079_45g2mb5",
        "status": "Passed"
      },
      {
        "testCaseId": "id_1776313890088_8st0q7u",
        "status": "Passed"
      },
      {
        "testCaseId": "id_1776313890098_nbhl7jm",
        "status": "Passed"
      },
      {
        "testCaseId": "id_1776313890107_5b5rdf8",
        "status": "Failed"
      },
      {
        "testCaseId": "id_1776313890115_28zohzb",
        "status": "Passed"
      },
      {
        "testCaseId": "id_1776313890125_rb3kel1",
        "status": "Passed"
      },
      {
        "testCaseId": "id_1776313890133_8z2j8ah",
        "status": "Passed"
      },
      {
        "testCaseId": "id_1776313890142_jdxcvbf",
        "status": "Passed"
      },
      {
        "testCaseId": "id_1776313890151_na3r3gf",
        "status": "Passed"
      },
      {
        "testCaseId": "id_1776313890190_9ql75bh",
        "status": "Passed"
      },
      {
        "testCaseId": "id_1776313890196_c42bjtq",
        "status": "Passed"
      },
      {
        "testCaseId": "id_1776313890206_crbov5y",
        "status": "Passed"
      },
      {
        "testCaseId": "id_1776313890214_i4u2s03",
        "status": "Passed"
      },
      {
        "testCaseId": "id_1776313890222_9e8m4sn",
        "status": "Passed"
      },
      {
        "testCaseId": "id_1776313890230_dleip9e",
        "status": "Passed"
      },
      {
        "testCaseId": "id_1776313890238_plldmw4",
        "status": "Passed"
      },
      {
        "testCaseId": "id_1776313890265_8quu0l8",
        "status": "Passed"
      },
      {
        "testCaseId": "id_1776313890271_unmza7p",
        "status": "Passed"
      },
      {
        "testCaseId": "id_1776313890277_nvf6i2k",
        "status": "Passed"
      },
      {
        "testCaseId": "id_1776313890284_mlatzna",
        "status": "Passed"
      },
      {
        "testCaseId": "id_1776313890292_c1qrace",
        "status": "Passed"
      },
      {
        "testCaseId": "id_1776313890300_nmd89rd",
        "status": "Passed"
      },
      {
        "testCaseId": "id_1776313890308_cecxl7l",
        "status": "Failed"
      },
      {
        "testCaseId": "id_1776313890317_qapm374",
        "status": "Failed"
      },
      {
        "testCaseId": "id_1776313890326_22y6cah",
        "status": "Passed"
      },
      {
        "testCaseId": "id_1776313890335_9g78vhs",
        "status": "Passed"
      },
      {
        "testCaseId": "id_1776313890344_wblb6q2",
        "status": "Passed"
      },
      {
        "testCaseId": "id_1776313890352_xdyseny",
        "status": "Passed"
      },
      {
        "testCaseId": "id_1776313890361_t1lhqew",
        "status": "Passed"
      },
      {
        "testCaseId": "id_1776313890369_zw361yc",
        "status": "Passed"
      },
      {
        "testCaseId": "id_1776313890377_df6wkxw",
        "status": "Passed"
      },
      {
        "testCaseId": "id_1776313890386_kx08byl",
        "status": "Passed"
      },
      {
        "testCaseId": "id_1776313890395_9100ddh",
        "status": "Passed"
      },
      {
        "testCaseId": "id_1776313890404_jwvbqlu",
        "status": "Passed"
      },
      {
        "testCaseId": "id_1776313890413_4uwjg5o",
        "status": "Passed"
      },
      {
        "testCaseId": "id_1776313890428_y2lm127",
        "status": "Passed"
      },
      {
        "testCaseId": "id_1776313890437_vnpssmk",
        "status": "Passed"
      },
      {
        "testCaseId": "id_1776313890447_we7whk4",
        "status": "Passed"
      },
      {
        "testCaseId": "id_1776313890481_fj7eadz",
        "status": "Passed"
      },
      {
        "testCaseId": "id_1776313890487_da23k47",
        "status": "Passed"
      },
      {
        "testCaseId": "id_1776313890494_99xeefc",
        "status": "Passed"
      },
      {
        "testCaseId": "id_1776313890502_u1ukbs9",
        "status": "Passed"
      },
      {
        "testCaseId": "id_1776313890511_5q12wo7",
        "status": "Passed"
      },
      {
        "testCaseId": "id_1776313890518_ndob66v",
        "status": "Passed"
      },
      {
        "testCaseId": "id_1776313890528_9877jr0",
        "status": "Passed"
      },
      {
        "testCaseId": "id_1776313890537_65tczrn",
        "status": "Passed"
      },
      {
        "testCaseId": "id_1776313890545_9qvzxvf",
        "status": "Passed"
      },
      {
        "testCaseId": "id_1776313890554_91fp4vw",
        "status": "Passed"
      },
      {
        "testCaseId": "id_1776313890562_giyxz1i",
        "status": "Passed"
      },
      {
        "testCaseId": "id_1776313890571_7k95d0o",
        "status": "Passed"
      },
      {
        "testCaseId": "id_1776313890579_i2ixuc4",
        "status": "Passed"
      },
      {
        "testCaseId": "id_1776313890588_tshykye",
        "status": "Passed"
      },
      {
        "testCaseId": "id_1776313890596_gmyjz3u",
        "status": "Passed"
      },
      {
        "testCaseId": "id_1776313890605_5a47gnb",
        "status": "Passed"
      },
      {
        "testCaseId": "id_1776313890614_pfyegir",
        "status": "Passed"
      },
      {
        "testCaseId": "id_1776313890622_fh38pp7",
        "status": "Failed"
      },
      {
        "testCaseId": "id_1776313890631_kqlhkuw",
        "status": "Passed"
      },
      {
        "testCaseId": "id_1776313890639_49qghv3",
        "status": "Passed"
      },
      {
        "testCaseId": "id_1776313890666_eq2olr9",
        "status": "Passed"
      },
      {
        "testCaseId": "id_1776313890672_i2agc9d",
        "status": "Passed"
      },
      {
        "testCaseId": "id_1776313890681_6wda0n8",
        "status": "Passed"
      },
      {
        "testCaseId": "id_1776313890690_51uhq47",
        "status": "Passed"
      },
      {
        "testCaseId": "id_1776313890698_metyohu",
        "status": "Passed"
      },
      {
        "testCaseId": "id_1776313890706_dywzi2h",
        "status": "Passed"
      },
      {
        "testCaseId": "id_1776313890713_mat8kj7",
        "status": "Passed"
      },
      {
        "testCaseId": "id_1776313890721_43wzzmo",
        "status": "Passed"
      },
      {
        "testCaseId": "id_1776313890730_ybeepo5",
        "status": "Passed"
      },
      {
        "testCaseId": "id_1776313890738_yjg0efk",
        "status": "Passed"
      },
      {
        "testCaseId": "id_1776313890746_ekaknki",
        "status": "Passed"
      },
      {
        "testCaseId": "id_1776313890755_c8cw1cx",
        "status": "Passed"
      },
      {
        "testCaseId": "id_1776313890763_k7r8qc7",
        "status": "Passed"
      },
      {
        "testCaseId": "id_1776313890771_ttpyp60",
        "status": "Passed"
      },
      {
        "testCaseId": "id_1776313890780_20d98zh",
        "status": "Passed"
      },
      {
        "testCaseId": "id_1776313890789_icjl7do",
        "status": "Passed"
      },
      {
        "testCaseId": "id_1776313890798_6fr7hnq",
        "status": "Passed"
      },
      {
        "testCaseId": "id_1776313890806_4wgau46",
        "status": "Passed"
      },
      {
        "testCaseId": "id_1776313890820_pmku3r3",
        "status": "Passed"
      },
      {
        "testCaseId": "id_1776313890859_ge3vjw2",
        "status": "Passed"
      },
      {
        "testCaseId": "id_1776313890866_qlaoenz",
        "status": "Passed"
      },
      {
        "testCaseId": "id_1776313890876_eb2tft1",
        "status": "Passed"
      },
      {
        "testCaseId": "id_1776313890884_kv9llvp",
        "status": "Passed"
      },
      {
        "testCaseId": "id_1776313890893_01sit3u",
        "status": "Passed"
      },
      {
        "testCaseId": "id_1776313890901_bw9z6b9",
        "status": "Passed"
      },
      {
        "testCaseId": "id_1776313890909_pcch6fj",
        "status": "Failed"
      },
      {
        "testCaseId": "id_1776313890918_1qyg7ld",
        "status": "Failed"
      },
      {
        "testCaseId": "id_1776313890926_r5t2dtc",
        "status": "Failed"
      },
      {
        "testCaseId": "id_1776313890936_xd4ucva",
        "status": "Passed"
      },
      {
        "testCaseId": "id_1776313890945_1cj7rtl",
        "status": "Passed"
      },
      {
        "testCaseId": "id_1776313890954_5xogi3q",
        "status": "Passed"
      },
      {
        "testCaseId": "id_1776313890963_4afhkzb",
        "status": "Passed"
      },
      {
        "testCaseId": "id_1776313890972_1cah8i8",
        "status": "Passed"
      },
      {
        "testCaseId": "id_1776313890982_fqnnlct",
        "status": "Failed"
      },
      {
        "testCaseId": "id_1776313890991_421gd81",
        "status": "Passed"
      },
      {
        "testCaseId": "id_1776313891001_ynbjy5e",
        "status": "Passed"
      },
      {
        "testCaseId": "id_1776313891010_tavvsvt",
        "status": "Passed"
      },
      {
        "testCaseId": "id_1776313891020_64m8ozf",
        "status": "Passed"
      },
      {
        "testCaseId": "id_1776313891030_pu22r1w",
        "status": "Passed"
      },
      {
        "testCaseId": "id_1776313891043_madnnuo",
        "status": "Passed"
      },
      {
        "testCaseId": "id_1776313891052_gonmo5n",
        "status": "Passed"
      },
      {
        "testCaseId": "id_1776313891061_09txybr",
        "status": "Passed"
      },
      {
        "testCaseId": "id_1776313891070_il6rymb",
        "status": "Passed"
      },
      {
        "testCaseId": "id_1776313891079_oiejo36",
        "status": "Passed"
      },
      {
        "testCaseId": "id_1776313891087_ysnzfhx",
        "status": "Passed"
      },
      {
        "testCaseId": "id_1776313891094_v25ljld",
        "status": "Passed"
      },
      {
        "testCaseId": "id_1776313891106_e7yu7w2",
        "status": "Passed"
      },
      {
        "testCaseId": "id_1776313891112_w7g2v9v",
        "status": "Passed"
      },
      {
        "testCaseId": "id_1776313891119_r69i7gj",
        "status": "Passed"
      },
      {
        "testCaseId": "id_1776313891125_ghndtg7",
        "status": "Passed"
      },
      {
        "testCaseId": "id_1776313891132_4q94dq5",
        "status": "Passed"
      },
      {
        "testCaseId": "id_1776313891139_urdbl2r",
        "status": "Passed"
      },
      {
        "testCaseId": "id_1776313891151_8rkmfoz",
        "status": "Passed"
      },
      {
        "testCaseId": "id_1776313891158_wc3s07x",
        "status": "Passed"
      },
      {
        "testCaseId": "id_1776313891165_cpimgu1",
        "status": "Passed"
      },
      {
        "testCaseId": "id_1776313891172_82r9pp1",
        "status": "Passed"
      },
      {
        "testCaseId": "id_1776313891179_3sqkrnf",
        "status": "Passed"
      },
      {
        "testCaseId": "id_1776313891186_q72zg74",
        "status": "Passed"
      },
      {
        "testCaseId": "id_1776313891193_mlpum0o",
        "status": "Passed"
      },
      {
        "testCaseId": "id_1776313891202_wi1kt0w",
        "status": "Passed"
      },
      {
        "testCaseId": "id_1776313891211_2vz2nan",
        "status": "Passed"
      },
      {
        "testCaseId": "id_1776313891218_5ytdz1k",
        "status": "Passed"
      },
      {
        "testCaseId": "id_1776313891228_axv7m70",
        "status": "Passed"
      },
      {
        "testCaseId": "id_1776313891236_33v9t6d",
        "status": "Passed"
      },
      {
        "testCaseId": "id_1776313891245_ypb330z",
        "status": "Passed"
      },
      {
        "testCaseId": "id_1776313891253_3hh8eqv",
        "status": "Passed"
      },
      {
        "testCaseId": "id_1776313891261_1p89oef",
        "status": "Passed"
      },
      {
        "testCaseId": "id_1776313891288_wx3tpag",
        "status": "Passed"
      },
      {
        "testCaseId": "id_1776313891295_qybet5o",
        "status": "Passed"
      },
      {
        "testCaseId": "id_1776313891301_s26jix4",
        "status": "Passed"
      },
      {
        "testCaseId": "id_1776313891310_qqhpuup",
        "status": "Passed"
      },
      {
        "testCaseId": "id_1776313891321_z2a1t5n",
        "status": "Passed"
      },
      {
        "testCaseId": "id_1776313891328_fqr89xc",
        "status": "Passed"
      },
      {
        "testCaseId": "id_1776313891336_absafah",
        "status": "Passed"
      },
      {
        "testCaseId": "id_1776313891344_hsmaa2n",
        "status": "Passed"
      },
      {
        "testCaseId": "id_1776313891351_3d8kn4d",
        "status": "Passed"
      },
      {
        "testCaseId": "id_1776313891361_0pq3hju",
        "status": "Passed"
      },
      {
        "testCaseId": "id_1776313891369_0msy5fm",
        "status": "Passed"
      },
      {
        "testCaseId": "id_1776313891378_t373h9q",
        "status": "Passed"
      },
      {
        "testCaseId": "id_1776313891386_u7k24vn",
        "status": "Passed"
      },
      {
        "testCaseId": "id_1776313891395_bkmkuqk",
        "status": "Passed"
      },
      {
        "testCaseId": "id_1776313891404_xumg6qz",
        "status": "Passed"
      },
      {
        "testCaseId": "id_1776313891417_o6faj54",
        "status": "Passed"
      },
      {
        "testCaseId": "id_1776313891426_0rtpjob",
        "status": "Passed"
      },
      {
        "testCaseId": "id_1776313891434_si5s1nw",
        "status": "Passed"
      },
      {
        "testCaseId": "id_1776313891442_x5684fr",
        "status": "Passed"
      },
      {
        "testCaseId": "id_1776313891450_7wkj6mt",
        "status": "Passed"
      },
      {
        "testCaseId": "id_1776313891484_196asza",
        "status": "Passed"
      },
      {
        "testCaseId": "id_1776313891493_t5o1j1i",
        "status": "Passed"
      },
      {
        "testCaseId": "id_1776313891503_31wlte3",
        "status": "Passed"
      },
      {
        "testCaseId": "id_1776313891511_lxqfmlr",
        "status": "Passed"
      },
      {
        "testCaseId": "id_1776313891519_pf4uq2o",
        "status": "Passed"
      },
      {
        "testCaseId": "id_1776313891528_mv62k5a",
        "status": "Passed"
      },
      {
        "testCaseId": "id_1776313891537_p6n46z0",
        "status": "Passed"
      },
      {
        "testCaseId": "id_1776313891546_gcsv5bk",
        "status": "Passed"
      },
      {
        "testCaseId": "id_1776313891555_ye775hn",
        "status": "Passed"
      },
      {
        "testCaseId": "id_1776313891565_qmd1poy",
        "status": "Passed"
      },
      {
        "testCaseId": "id_1776313891574_iijwh6o",
        "status": "Passed"
      },
      {
        "testCaseId": "id_1776313891583_ztxgvkk",
        "status": "Passed"
      },
      {
        "testCaseId": "id_1776313891592_ifm8tt0",
        "status": "Passed"
      },
      {
        "testCaseId": "id_1776313891607_7t9469d",
        "status": "Passed"
      },
      {
        "testCaseId": "id_1776313891616_myrb456",
        "status": "Passed"
      },
      {
        "testCaseId": "id_1776313891626_6yg3m5f",
        "status": "Passed"
      },
      {
        "testCaseId": "id_1776313891634_wz5qecq",
        "status": "Passed"
      },
      {
        "testCaseId": "id_1776313891643_jxt23tz",
        "status": "Passed"
      },
      {
        "testCaseId": "id_1776313891651_s08jw7n",
        "status": "Passed"
      },
      {
        "testCaseId": "id_1776313891660_w84n4ph",
        "status": "Passed"
      },
      {
        "testCaseId": "id_1776313891693_96i0dnh",
        "status": "Passed"
      },
      {
        "testCaseId": "id_1776313891701_1utg02h",
        "status": "Skipped"
      },
      {
        "testCaseId": "id_1776313891711_4v1x60m",
        "status": "Skipped"
      },
      {
        "testCaseId": "id_1776313891719_2deiop3",
        "status": "Skipped"
      },
      {
        "testCaseId": "id_1776313891727_p87pnvu",
        "status": "Skipped"
      },
      {
        "testCaseId": "id_1776313891736_wgqp1bu",
        "status": "Skipped"
      },
      {
        "testCaseId": "id_1776313891745_rpcp66s",
        "status": "Skipped"
      }
    ],
    "id": "id_1776314102217_7530rr0"
  }
]